<INVENTORY>
 <ITEM>
   <ITEMID>4073</ITEMID>
     <ITEMTYPE>P</ITEMTYPE>
       <COLOR>11</COLOR>
         <MINQTY>40</MINQTY>
    </ITEM>
     <ITEM>
       <ITEMID>44728</ITEMID>
         <ITEMTYPE>P</ITEMTYPE>
   <COLOR>11</COLOR>
     <MINQTY>5</MINQTY>
      </ITEM>
       <ITEM>
         <ITEMID>2921</ITEMID>
   <ITEMTYPE>P</ITEMTYPE>
     <COLOR>11</COLOR>
       <MINQTY>5</MINQTY>
        </ITEM>
 <ITEM>
   <ITEMID>4595</ITEMID>
     <ITEMTYPE>P</ITEMTYPE>
       <COLOR>11</COLOR>
         <MINQTY>10</MINQTY>
  </ITEM>
   <ITEM>
     <ITEMID>553b</ITEMID>
       <ITEMTYPE>P</ITEMTYPE>
         <COLOR>11</COLOR>
   <MINQTY>5</MINQTY>
    </ITEM>
     <ITEM>
       <ITEMID>4740</ITEMID>
         <ITEMTYPE>P</ITEMTYPE>
   <COLOR>11</COLOR>
     <MINQTY>5</MINQTY>
      </ITEM>
       <ITEM>
         <ITEMID>43898</ITEMID>
   <ITEMTYPE>P</ITEMTYPE>
     <COLOR>11</COLOR>
       <MINQTY>5</MINQTY>
        </ITEM>
 <ITEM>
   <ITEMID>64644</ITEMID>
     <ITEMTYPE>P</ITEMTYPE>
       <COLOR>11</COLOR>
         <MINQTY>5</MINQTY>
  </ITEM>
   <ITEM>
     <ITEMID>3023</ITEMID>
       <ITEMTYPE>P</ITEMTYPE>
         <COLOR>11</COLOR>
   <MINQTY>10</MINQTY>
    </ITEM>
     <ITEM>
       <ITEMID>6019</ITEMID>
         <ITEMTYPE>P</ITEMTYPE>
   <COLOR>11</COLOR>
     <MINQTY>5</MINQTY>
      </ITEM>
       <ITEM>
         <ITEMID>4081b</ITEMID>
   <ITEMTYPE>P</ITEMTYPE>
     <COLOR>11</COLOR>
       <MINQTY>10</MINQTY>
        </ITEM>
 <ITEM>
   <ITEMID>60478</ITEMID>
     <ITEMTYPE>P</ITEMTYPE>
       <COLOR>11</COLOR>
         <MINQTY>20</MINQTY>
  </ITEM>
   <ITEM>
     <ITEMID>3839b</ITEMID>
       <ITEMTYPE>P</ITEMTYPE>
         <COLOR>11</COLOR>
   <MINQTY>5</MINQTY>
    </ITEM>
     <ITEM>
       <ITEMID>30033</ITEMID>
         <ITEMTYPE>P</ITEMTYPE>
   <COLOR>11</COLOR>
     <MINQTY>5</MINQTY>
      </ITEM>
       <ITEM>
         <ITEMID>2780</ITEMID>
   <ITEMTYPE>P</ITEMTYPE>
     <COLOR>11</COLOR>
       <MINQTY>5</MINQTY>
        </ITEM>
 <ITEM>
   <ITEMID>2555</ITEMID>
     <ITEMTYPE>P</ITEMTYPE>
       <COLOR>11</COLOR>
         <MINQTY>5</MINQTY>
  </ITEM>
   <ITEM>
     <ITEMID>6091</ITEMID>
       <ITEMTYPE>P</ITEMTYPE>
         <COLOR>86</COLOR>
   <MINQTY>10</MINQTY>
    </ITEM>
     <ITEM>
       <ITEMID>4740</ITEMID>
         <ITEMTYPE>P</ITEMTYPE>
   <COLOR>86</COLOR>
     <MINQTY>50</MINQTY>
      </ITEM>
       <ITEM>
         <ITEMID>3022</ITEMID>
   <ITEMTYPE>P</ITEMTYPE>
     <COLOR>86</COLOR>
       <MINQTY>5</MINQTY>
        </ITEM>
 <ITEM>
   <ITEMID>6019</ITEMID>
     <ITEMTYPE>P</ITEMTYPE>
       <COLOR>86</COLOR>
         <MINQTY>10</MINQTY>
  </ITEM>
   <ITEM>
     <ITEMID>4081b</ITEMID>
       <ITEMTYPE>P</ITEMTYPE>
         <COLOR>86</COLOR>
   <MINQTY>10</MINQTY>
    </ITEM>
     <ITEM>
       <ITEMID>60478</ITEMID>
         <ITEMTYPE>P</ITEMTYPE>
   <COLOR>86</COLOR>
     <MINQTY>10</MINQTY>
      </ITEM>
       <ITEM>
         <ITEMID>2540</ITEMID>
   <ITEMTYPE>P</ITEMTYPE>
     <COLOR>86</COLOR>
       <MINQTY>5</MINQTY>
         <MAXPRICE>0.032</MAXPRICE>
  </ITEM>
   <ITEM>
     <ITEMID>3700</ITEMID>
       <ITEMTYPE>P</ITEMTYPE>
         <COLOR>86</COLOR>
   <MINQTY>5</MINQTY>
    </ITEM>
     <ITEM>
       <ITEMID>2555</ITEMID>
         <ITEMTYPE>P</ITEMTYPE>
   <COLOR>86</COLOR>
     <MINQTY>45</MINQTY>
      </ITEM>
       <ITEM>
         <ITEMID>30602</ITEMID>
   <ITEMTYPE>P</ITEMTYPE>
     <COLOR>5</COLOR>
       <MINQTY>10</MINQTY>
        </ITEM>
 <ITEM>
   <ITEMID>3005</ITEMID>
     <ITEMTYPE>P</ITEMTYPE>
       <COLOR>11</COLOR>
         <MINQTY>5</MINQTY>
  </ITEM>
   <ITEM>
     <ITEMID>49668</ITEMID>
       <ITEMTYPE>P</ITEMTYPE>
         <COLOR>11</COLOR>
   <MINQTY>20</MINQTY>
    </ITEM>
     <ITEM>
       <ITEMID>4599</ITEMID>
         <ITEMTYPE>P</ITEMTYPE>
   <COLOR>11</COLOR>
     <MINQTY>5</MINQTY>
      </ITEM>
       <ITEM>
         <ITEMID>2654</ITEMID>
   <ITEMTYPE>P</ITEMTYPE>
     <COLOR>86</COLOR>
       <MINQTY>5</MINQTY>
        </ITEM>
 <ITEM>
   <ITEMID>54200</ITEMID>
     <ITEMTYPE>P</ITEMTYPE>
       <COLOR>86</COLOR>
         <MINQTY>20</MINQTY>
  </ITEM>
   <ITEM>
     <ITEMID>3070b</ITEMID>
       <ITEMTYPE>P</ITEMTYPE>
         <COLOR>86</COLOR>
   <MINQTY>20</MINQTY>
    </ITEM>
     <ITEM>
       <ITEMID>3062b</ITEMID>
         <ITEMTYPE>P</ITEMTYPE>
   <COLOR>1</COLOR>
     <MINQTY>10</MINQTY>
      </ITEM>
       <ITEM>
         <ITEMID>3024</ITEMID>
   <ITEMTYPE>P</ITEMTYPE>
     <COLOR>11</COLOR>
       <MINQTY>10</MINQTY>
        </ITEM>
 <ITEM>
   <ITEMID>3024</ITEMID>
     <ITEMTYPE>P</ITEMTYPE>
       <COLOR>86</COLOR>
         <MINQTY>30</MINQTY>
  </ITEM>
   <ITEM>
     <ITEMID>3023</ITEMID>
       <ITEMTYPE>P</ITEMTYPE>
         <COLOR>86</COLOR>
   <MINQTY>5</MINQTY>
    </ITEM>
     <ITEM>
       <ITEMID>3069b</ITEMID>
         <ITEMTYPE>P</ITEMTYPE>
   <COLOR>86</COLOR>
     <MINQTY>35</MINQTY>
      </ITEM>
       <ITEM>
         <ITEMID>4733</ITEMID>
   <ITEMTYPE>P</ITEMTYPE>
     <COLOR>11</COLOR>
       <MINQTY>25</MINQTY>
        </ITEM>
 <ITEM>
   <ITEMID>3794</ITEMID>
     <ITEMTYPE>P</ITEMTYPE>
       <COLOR>86</COLOR>
         <MINQTY>15</MINQTY>
  </ITEM>
   <ITEM>
     <ITEMID>4070</ITEMID>
       <ITEMTYPE>P</ITEMTYPE>
         <COLOR>86</COLOR>
   <MINQTY>20</MINQTY>
    </ITEM>
     <ITEM>
       <ITEMID>4599</ITEMID>
         <ITEMTYPE>P</ITEMTYPE>
   <COLOR>86</COLOR>
     <MINQTY>20</MINQTY>
      </ITEM>
       <ITEM>
         <ITEMID>4032b</ITEMID>
   <ITEMTYPE>P</ITEMTYPE>
     <COLOR>86</COLOR>
       <MINQTY>5</MINQTY>
        </ITEM>
 <ITEM>
   <ITEMID>30031</ITEMID>
     <ITEMTYPE>P</ITEMTYPE>
       <COLOR>11</COLOR>
         <MINQTY>10</MINQTY>
  </ITEM>
   <ITEM>
     <ITEMID>48729</ITEMID>
       <ITEMTYPE>P</ITEMTYPE>
         <COLOR>11</COLOR>
   <MINQTY>10</MINQTY>
    </ITEM>
    </INVENTORY>
